pylibde265-0.1.0.dist-info/RECORD
pylibde265-0.1.0.dist-info/WHEEL
pylibde265-0.1.0.dist-info/METADATA
pylibde265-0.1.0.dist-info/licenses/LICENSE
pylibde265/_visualize.cpython-314-darwin.so
pylibde265/visualize.pyi
pylibde265/visualize_pybind.cpp
pylibde265/de265_pybind.cpp
pylibde265/de265.pyi
pylibde265/__init__.py
pylibde265/visualize.py
pylibde265/demuxer.h
pylibde265/py.typed
pylibde265/minimp4.h
pylibde265/de265.py
pylibde265/_de265.cpython-314-darwin.so
bin/dec265
include/libde265/de265.h
include/libde265/en265.h
include/libde265/de265-version.h
lib/libde265.a
lib/pkgconfig/libde265.pc
lib/cmake/libde265/libde265Config.cmake
lib/cmake/libde265/libde265Config-release.cmake
lib/cmake/libde265/libde265ConfigVersion.cmake
