Metadata-Version: 2.2
Name: pylibde265
Version: 0.1.0
Summary: Decode HEVC(H.265) video in python
Keywords: libde265,h265,video,decode,mp4,hevc,python
Author-Email: =?utf-8?b?5qKm5b2S5LqR5biG?= <1138663075@qq.com>
License: GPL-3.0-or-later
Classifier: Programming Language :: Python :: 3
Classifier: Programming Language :: C++
Classifier: Operating System :: Microsoft :: Windows
Classifier: Operating System :: POSIX :: Linux
Classifier: Operating System :: MacOS
Project-URL: Homepage, https://github.com/Puiching-Memory/pylibde265
Project-URL: Issues, https://github.com/Puiching-Memory/pylibde265/issues
Requires-Python: >=3.9
Requires-Dist: numpy>=2.0.0
Provides-Extra: dev
Requires-Dist: pybind11>=2.12.0; extra == "dev"
Requires-Dist: cmake>=4.2.0; extra == "dev"
Requires-Dist: build>=1.2.0; extra == "dev"
Requires-Dist: pytest>=8.0.0; extra == "dev"
